cli/__init__.py
cli/main.py
cli/ansible_parser/__init__.py
cli/ansible_parser/inventory_parser.py
ansible_terminal-0.14.1.dist-info/LICENSE
ansible_terminal-0.14.1.dist-info/METADATA
ansible_terminal-0.14.1.dist-info/WHEEL
ansible_terminal-0.14.1.dist-info/entry_points.txt
ansible_terminal-0.14.1.dist-info/top_level.txt
ansible_terminal-0.14.1.dist-info/RECORD
